basalunit/__init__.py
basalunit/utils.py
basalunit/capabilities/__init__.py
basalunit/capabilities/cap_SnuddaBasedModel.py
basalunit/plots/__init__.py
basalunit/plots/plot_errors_absolute.py
basalunit/plots/plot_errors_relative.py
basalunit/plots/plot_json_data.py
basalunit/plots/plot_model_exp_traces.py
basalunit/plots/plot_txt_table.py
basalunit/scores/__init__.py
basalunit/scores/score_AvgRelativeDifferenceScore_ConnProb.py
basalunit/scores/score_BasicZScore.py
basalunit/scores/score_CohenDScore.py
basalunit/scores/score_CustomZScore_NeuroModulation.py
basalunit/scores/score_KLdivMeanStd.py
basalunit/scores/score_ZScore.py
basalunit/tests/__init__.py
basalunit/tests/test_connectivityTest.py
basalunit/tests/test_eFELFeaturesTest.py
basalunit/tests/test_neuromodulationTest.py
basalunit/tests/test_pairPulseTest.py
basalunit/tests/somafeat_stim/YJ150915_c67D1ch01D2ch23-c6-protocols.json
basalunit/tests/somafeat_stim/YJ150915_c67D1ch01D2ch23-c7-protocols.json
basalunit/tests/somafeat_stim/str-fs-161205_FS1-protocols.json
basalunit-1.1.0.dist-info/LICENSE.txt
basalunit-1.1.0.dist-info/METADATA
basalunit-1.1.0.dist-info/WHEEL
basalunit-1.1.0.dist-info/top_level.txt
basalunit-1.1.0.dist-info/RECORD
