Metadata-Version: 2.1
Name: basalunit
Version: 1.1.0
Summary: A SciUnit library for data-driven testing of basal ganglia models.
Home-page: https://github.com/appukuttan-shailesh/basalunit
Author: Shailesh Appukuttan
Author-email: shailesh.appukuttan@unic.cnrs-gif.fr
License: MIT
Keywords: basal ganglia,electrical,efel,bluepyopt,validation framework
Platform: UNKNOWN
Requires-Dist: elephant
Requires-Dist: neo
Requires-Dist: sciunit (>=0.2.7)
Requires-Dist: tabulate
